{
  "recentFiles": [
    {
      "basename": "Índice Front-End",
      "path": "‎ Front-End/Índice Front-End.md"
    },
    {
      "basename": "Meta",
      "path": "‎ Front-End/Meta.md"
    },
    {
      "basename": "Flashcards Front-End",
      "path": "Organização/Flashcards/Flashcards Front-End.md"
    },
    {
      "basename": "URL e URI",
      "path": "‎ Front-End/URL e URI.md"
    }
  ],
  "omittedPaths": [],
  "omittedTags": [
    "ignore",
    "Images/"
  ],
  "updateOn": "file-open",
  "omitBookmarks": false,
  "maxLength": 4
}